{"url": "https://www.businesswire.com/news/home/20190308005002/en/GigCapital-Confirms-Receipt-Sponsor-Founder-Funds-Extend", "body": "PALO ALTO, Calif.--(BUSINESS WIRE)--GigCapital, Inc., (NYSE: GIG, GIG.U, GIG.RT, and GIG.WS) (\u201cGigCapital\u201d) a Technology, Media and Telecom (TMT) Private-to-Public Equity (PPE)\u2122 corporation, today announced that the GigCapital Sponsor and Founders collectively have deposited into the GigCapital trust account (the \u201cTrust Account\u201d) an aggregate of $1,437,500.00, representing $0.10 per public share. As a result of the deposit into the Trust Account, the period of time that GigCapital has to complete the previously announced proposed transaction with Kaleyra S.p.A. has been extended by three months until June 12, 2019.\n\nAbout GigCapital, Inc.\n\nGigCapital, Inc. (NYSE: GIG, GIG.U, GIG.RT, and GIG.WS), is a Private-to-Public Equity (PPE)\u2122 company, (also known as a Blank-Check or Special Purpose Acquisition Company (\u201cSPAC\u201d)), sponsored by GigAcquisitions, LLC, and sole-managed by GigFounders, LLC (www.gigfoundersglobal.com). All were founded in 2017 by Dr. Avi Katz. The GigCapital Group companies are led by an affiliated team of technology industry experts, deploying a unique Mentor-Investors\u2122 methodology to partner with exceptional privately-held and non-U.S. public technology companies of dedicated solid entrepreneurs. The GigCapital Group companies offer financial, operational and executive mentoring to U.S. and global private, and non-U.S. public companies, in order to accelerate their path from inception and as a privately-held entity into the growth-stage as a publicly traded company in the U.S. The partnership of the GigCapital Group with these companies continues through an organic and roll-up strategy growth post the transition to a public company. For more information, visit www.gigcapitalglobal.com.\n\n\u201cPrivate-to-Public Equity (PPE)\u201d and \u201cMentor-Investor\u201d are trademarks of GigFounders, LLC, used pursuant to agreement.", "title": "GigCapital, Inc. Confirms Receipt of Sponsor and Founder Funds to Extend Period of Time to Consummate Business Combination", "images": [], "text": "![Business Wire](/images/bwlogo_extreme.png)\n\n# GigCapital, Inc. Confirms Receipt of Sponsor and Founder Funds to Extend\nPeriod of Time to Consummate Business Combination\n\nMarch 08, 2019 04:10 PM Eastern Standard Time\n\nPALO ALTO, Calif.--(BUSINESS WIRE)--GigCapital, Inc., (NYSE: GIG, GIG.U,\nGIG.RT, and GIG.WS) (\u201cGigCapital\u201d) a Technology, Media and Telecom (TMT)\nPrivate-to-Public Equity (PPE)\u2122 corporation, today announced that the\nGigCapital Sponsor and Founders collectively have deposited into the\nGigCapital trust account (the \u201cTrust Account\u201d) an aggregate of $1,437,500.00,\nrepresenting $0.10 per public share. As a result of the deposit into the Trust\nAccount, the period of time that GigCapital has to complete the previously\nannounced proposed transaction with Kaleyra S.p.A. has been extended by three\nmonths until June 12, 2019.\n\nAbout GigCapital, Inc.\n\nGigCapital, Inc. (NYSE: GIG, GIG.U, GIG.RT, and GIG.WS), is a Private-to-\nPublic Equity (PPE)\u2122 company, (also known as a Blank-Check or Special Purpose\nAcquisition Company (\u201cSPAC\u201d)), sponsored by GigAcquisitions, LLC, and sole-\nmanaged by GigFounders, LLC (www.gigfoundersglobal.com). All were founded in\n2017 by Dr. Avi Katz. The GigCapital Group companies are led by an affiliated\nteam of technology industry experts, deploying a unique Mentor-Investors\u2122\nmethodology to partner with exceptional privately-held and non-U.S. public\ntechnology companies of dedicated solid entrepreneurs. The GigCapital Group\ncompanies offer financial, operational and executive mentoring to U.S. and\nglobal private, and non-U.S. public companies, in order to accelerate their\npath from inception and as a privately-held entity into the growth-stage as a\npublicly traded company in the U.S. The partnership of the GigCapital Group\nwith these companies continues through an organic and roll-up strategy growth\npost the transition to a public company. For more information, visit\nwww.gigcapitalglobal.com.\n\n\u201cPrivate-to-Public Equity (PPE)\u201d and \u201cMentor-Investor\u201d are trademarks of\nGigFounders, LLC, used pursuant to agreement.\n\n## Contacts\n\nGigCapital: \nDarrow Associates, Inc. \nJim Fanucchi \n+1 (408) 404-5400 \nir@gigcapitalglobal.com\n\n## Contacts\n\nGigCapital: \nDarrow Associates, Inc. \nJim Fanucchi \n+1 (408) 404-5400 \nir@gigcapitalglobal.com\n\n## Site Navigation\n\n Home\n Home\n Submit a Press Release\n Services\n News\n All News\n News with Multimedia\n News by Industry\n News by Subject\n News by Language\n Tradeshows & Events\n Education\n Overview\n Distribution & Media\n Media & Journalist Tools\n Sample Press Release\n Find Your News Online\n How-to\n Disclosure Resources\n About Us\n Overview\n Become a Member\n Contact Us\n Follow Us\n Careers\n Business Wire Newsroom\n Business Wire Events\n\n## Search\n\nAdvanced News Search\n\nAdvanced News Search ![Search](/images/icons/icon_search.gif)\n\n Log In\n Sign Up\n\n## Follow Us\n\n Twitter\n LinkedIn\n Google+\n\n## More from Business Wire\n\n Blog\n Apps\n UK/Ireland\n Deutschland\n France\n Hong Kong\n Italy\n Japan\n Tradeshownews.com\n\n## Business Wire Information\n\n Contact Us\n UK Tax Strategy\n Privacy Statement\n Terms of Use\n (C) 2019 Business Wire\n\nAccept the use of cookies Learn more\n\nI Accept\n\n", "contact_info": [{"name": "Jim Fanucchi", "phone": "+1 (408) 404-5400", "email": "ir@gigcapitalglobal.com"}], "date": "March 08, 2019 04:10 PM Eastern Standard Time", "published_date_time": "March 08, 2019 04:10 PM Eastern Standard Time", "entities": [], "company_1": "GigCapital, Inc.", "company_2": "Public Equity"}